bitops/BinaryOperations.py
bitops/__init__.py
bitops-0.0.5.dist-info/LICENSE
bitops-0.0.5.dist-info/METADATA
bitops-0.0.5.dist-info/WHEEL
bitops-0.0.5.dist-info/top_level.txt
bitops-0.0.5.dist-info/RECORD
