Metadata-Version: 2.1
Name: bitops
Version: 0.0.5
Summary: Simple bit manipulations for personal projects
Home-page: https://github.com/vitalij555/binary-operations
Author: Vitalij Gotovskij
Author-email: vitalij@cdeveloper.eu
License: MIT
Keywords: BINARY,OPERATIONS,BITWISE,MATH,BITS,BYTES
Classifier: Development Status :: 3 - Alpha
Classifier: Intended Audience :: Developers
Classifier: Topic :: Software Development :: Build Tools
Classifier: Operating System :: OS Independent
Classifier: License :: OSI Approved :: MIT License
Classifier: Programming Language :: Python :: 3
Classifier: Programming Language :: Python :: 3.8
Classifier: Programming Language :: Python :: 3.9
Classifier: Programming Language :: Python :: 3.10
Classifier: Programming Language :: Python :: 3.11
Classifier: Programming Language :: Python :: 3.12
License-File: LICENSE
